cosmo_torrent/__init__.py
cosmo_torrent/cli.py
cosmo_torrent/cosmo_torrent.py
cosmo_torrent/vars.py
cosmo_torrent-0.2.0.dist-info/METADATA
cosmo_torrent-0.2.0.dist-info/WHEEL
cosmo_torrent-0.2.0.dist-info/entry_points.txt
cosmo_torrent-0.2.0.dist-info/licenses/AUTHORS.rst
cosmo_torrent-0.2.0.dist-info/licenses/LICENSE
cosmo_torrent-0.2.0.dist-info/RECORD
