Metadata-Version: 2.3
Name: cosmo-torrent
Version: 0.2.0
Summary: Data downloader library for Cosmology related data
Project-URL: Repository, https://cosmo-docs.phys.ethz.ch/cosmo-torrent
Author-email: Uwe Schmitt <uwe.schmitt@id.ethz.ch>
License: MIT License
License-File: AUTHORS.rst
License-File: LICENSE
Classifier: Intended Audience :: Developers
Classifier: Intended Audience :: Science/Research
Classifier: License :: OSI Approved :: MIT License
Classifier: Natural Language :: English
Classifier: Operating System :: OS Independent
Classifier: Programming Language :: Python :: 3
Classifier: Programming Language :: Python :: 3.9
Classifier: Programming Language :: Python :: 3.10
Requires-Dist: beautifulsoup4
Requires-Dist: click
Requires-Dist: requests
Requires-Dist: tqdm
Provides-Extra: dev
Requires-Dist: build; extra == 'dev'
Requires-Dist: isort; extra == 'dev'
Requires-Dist: pre-commit; extra == 'dev'
Requires-Dist: pytest; extra == 'dev'
Requires-Dist: pytest-cov; extra == 'dev'
Requires-Dist: pytest-regtest; extra == 'dev'
Requires-Dist: ruff; extra == 'dev'
Requires-Dist: twine; extra == 'dev'
Provides-Extra: docs
Requires-Dist: myst-parser; extra == 'docs'
Requires-Dist: sphinx-pynpoint-theme; extra == 'docs'
Requires-Dist: sphinx<7; extra == 'docs'
